pycosep/__init__.py
pycosep/community_separability.py
pycosep/concorde_settings.py
pycosep/separability_variants.py
tests/__init__.py
tests/test_concorde_settings.py
tests/test_cps_community_separability.py
tests/test_data.py
tests/test_ldps_community_separability.py
tests/test_tsps_community_separability.py
pycosep-0.2.0.dist-info/LICENSE.md
pycosep-0.2.0.dist-info/METADATA
pycosep-0.2.0.dist-info/WHEEL
pycosep-0.2.0.dist-info/top_level.txt
pycosep-0.2.0.dist-info/RECORD
