Metadata-Version: 2.1
Name: pycosep
Version: 0.2.0
Summary: Travelling Salesman Path - Python wrapper
Home-page: https://github.com/aacevedot/pycosep
Author: Dr. Aldo Acevedo
Author-email: aldo.acevedo.toledo@gmail.com
License: MIT
Classifier: Intended Audience :: Science/Research
Classifier: License :: OSI Approved :: MIT License
Classifier: Operating System :: OS Independent
Classifier: Programming Language :: Python :: 3
Classifier: Topic :: System :: Clustering
Requires-Python: >=3.9
License-File: LICENSE.md
Requires-Dist: numpy>=1.20
Requires-Dist: scipy>=1.6
Requires-Dist: scikit-learn>=0.24
Requires-Dist: networkx>=3.2
Provides-Extra: dev
Requires-Dist: pytest>=6.2; extra == "dev"
Requires-Dist: coverage>=5.5; extra == "dev"
Requires-Dist: flake8>=3.9; extra == "dev"
